django_secrets/__init__.py
django_secrets/utils.py
django_secrets/backends/__init__.py
django_secrets/backends/aws_secrets_manager.py
django_secrets/backends/secrets.py
django_secrets_manager-0.1.13.dist-info/LICENSE
django_secrets_manager-0.1.13.dist-info/METADATA
django_secrets_manager-0.1.13.dist-info/WHEEL
django_secrets_manager-0.1.13.dist-info/top_level.txt
django_secrets_manager-0.1.13.dist-info/zip-safe
django_secrets_manager-0.1.13.dist-info/RECORD
