Metadata-Version: 2.1
Name: django-secrets-manager
Version: 0.1.13
Summary: Django SecretsManager is custom secret managers for Django
Home-page: https://github.com/LeeHanYeong/django-secrets-manager
Author: Lee HanYeong
Author-email: dev@lhy.kr
License: MIT
Platform: UNKNOWN
Classifier: Framework :: Django
Classifier: Programming Language :: Python
Requires-Python: >3.5
Requires-Dist: boto3
Requires-Dist: django
